tess_atlas/__init__.py
tess_atlas/cfg.py
tess_atlas/config.py
tess_atlas/tess_atlas_version.py
tess_atlas/utils.py
tess_atlas/analysis/__init__.py
tess_atlas/analysis/eccenticity_reweighting.py
tess_atlas/analysis/gp.py
tess_atlas/analysis/model_tools.py
tess_atlas/analysis/stats_plotter.py
tess_atlas/api/__init__.py
tess_atlas/api/download_analysed_toi.py
tess_atlas/data/__init__.py
tess_atlas/data/data_object.py
tess_atlas/data/exofop.py
tess_atlas/data/inference_data_tools.py
tess_atlas/data/lightcurve_data.py
tess_atlas/data/planet_candidate.py
tess_atlas/data/stellar_data.py
tess_atlas/data/tic_entry.py
tess_atlas/notebook_preprocessors/__init__.py
tess_atlas/notebook_preprocessors/notebook_executor.py
tess_atlas/notebook_preprocessors/run_load_samples_demo.py
tess_atlas/notebook_preprocessors/run_toi.py
tess_atlas/notebook_preprocessors/run_tois.py
tess_atlas/notebook_preprocessors/toi_notebook_generator.py
tess_atlas/notebook_templates/load_samples_demo.py
tess_atlas/notebook_templates/toi_template.py
tess_atlas/plotting/__init__.py
tess_atlas/plotting/corner_plotter.py
tess_atlas/plotting/histogram_plotter.py
tess_atlas/plotting/labels.py
tess_atlas/plotting/matplotlib_plots.py
tess_atlas/plotting/plotly_plots.py
tess_atlas/plotting/plotter_backend.py
tess_atlas/plotting/plotting_utils.py
tess_atlas/plotting/extra_plotting/__init__.py
tess_atlas/plotting/extra_plotting/ci.py
tess_atlas/slurm_job_generator/__init__.py
tess_atlas/slurm_job_generator/file_generators.py
tess_atlas/slurm_job_generator/slurm_cli.py
tess_atlas/slurm_job_generator/slurm_job_generator.py
tess_atlas/slurm_job_generator/slurm_template.sh
tess_atlas/slurm_job_generator/slurm_utils.py
tess_atlas/slurm_job_generator/submit_template.sh
tess_atlas/webbuilder/__init__.py
tess_atlas/webbuilder/build_pages.py
tess_atlas/webbuilder/make_tois_homepage.py
tess_atlas-0.0.3a0.dist-info/LICENSE
tess_atlas-0.0.3a0.dist-info/METADATA
tess_atlas-0.0.3a0.dist-info/WHEEL
tess_atlas-0.0.3a0.dist-info/entry_points.txt
tess_atlas-0.0.3a0.dist-info/top_level.txt
tess_atlas-0.0.3a0.dist-info/zip-safe
tess_atlas-0.0.3a0.dist-info/RECORD
