Metadata-Version: 2.1
Name: tess-atlas
Version: 0.0.3a0
Summary: All the TESS exoplanets!
Home-page: https://github.com/dfm/tess-atlas
Author: Avi Vajpeyi & Dan Foreman-Mackey
Author-email: foreman.mackey@gmail.com
Maintainer: Avi Vajpeyi & Dan Foreman-Mackey
Maintainer-email: foreman.mackey@gmail.com
License: MIT
Platform: UNKNOWN
Classifier: Development Status :: 5 - Production/Stable
Classifier: Intended Audience :: Developers
Classifier: Intended Audience :: Science/Research
Classifier: License :: OSI Approved :: MIT License
Classifier: Operating System :: OS Independent
Classifier: Programming Language :: Python
Classifier: Programming Language :: Python :: 3
License-File: LICENSE
Requires-Dist: tomli (>=1.0.0)
Requires-Dist: docutils (==0.16)
Requires-Dist: exoplanet (>=0.5.1)
Requires-Dist: pymc3-ext (>=0.1.0)
Requires-Dist: theano-pymc (>=1.1.2)
Requires-Dist: celerite2 (>=0.2.0)
Requires-Dist: lightkurve (>=2.0.11)
Requires-Dist: plotly (>=4.9.0)
Requires-Dist: arviz (>=0.10.0)
Requires-Dist: corner (>=2.2.1)
Requires-Dist: seaborn
Requires-Dist: nbconvert (~=5.6)
Requires-Dist: jupyter-client (==6.1.12)
Requires-Dist: jupyter-book
Requires-Dist: click (~=7.1)
Provides-Extra: dev
Requires-Dist: pytest (>=3.6) ; extra == 'dev'
Requires-Dist: testbook (>=0.2.3) ; extra == 'dev'
Requires-Dist: pre-commit ; extra == 'dev'
Requires-Dist: flake8 ; extra == 'dev'
Requires-Dist: black ; extra == 'dev'
Requires-Dist: isort ; extra == 'dev'
Requires-Dist: jupyter-contrib-nbextensions ; extra == 'dev'
Provides-Extra: test
Requires-Dist: pytest (>=3.6) ; extra == 'test'
Requires-Dist: testbook (>=0.2.3) ; extra == 'test'
